rwavalidator.py
rwavalidator-0.0.2.dist-info/LICENSE
rwavalidator-0.0.2.dist-info/METADATA
rwavalidator-0.0.2.dist-info/WHEEL
rwavalidator-0.0.2.dist-info/top_level.txt
rwavalidator-0.0.2.dist-info/RECORD
