Metadata-Version: 2.1
Name: rwavalidator
Version: 0.0.2
Summary: A fast minimal package to validate Rwandan National Ids and Phone Numbers(all carriers) using Regular Expressions.
Home-page: UNKNOWN
Author: Igwaneza Bruce
Author-email: knowbeeinc@gmail.com
License: MIT
Keywords: rwanda,validator,rwavalidator,validate,id
Platform: UNKNOWN
Classifier: Programming Language :: Python
Classifier: Programming Language :: Python :: 3.7
Classifier: Intended Audience :: Developers
Classifier: Intended Audience :: Education
Classifier: License :: OSI Approved :: GNU General Public License (GPL)
Classifier: Operating System :: OS Independent
Requires-Python: >=3.6
